{
  "resources": [
    {
      "name": "Authentication",
      "explanation": null,
      "examples": [
        {
          "description": "Creating a new  User",
          "link": "authentication/creating_a_new_user.json",
          "groups": "all",
          "route": "signup",
          "method": "post"
        },
        {
          "description": "Creating a new token",
          "link": "authentication/creating_a_new_token.json",
          "groups": "all",
          "route": "auth/login",
          "method": "post"
        }
      ]
    },
    {
      "name": "Item",
      "explanation": null,
      "examples": [
        {
          "description": "Listing todos items",
          "link": "item/listing_todos_items.json",
          "groups": "all",
          "route": "/projects/:project_id/todos/:todo_id/items",
          "method": "get"
        },
        {
          "description": "Getting a specific item from the login user",
          "link": "item/getting_a_specific_item_from_the_login_user.json",
          "groups": "all",
          "route": "/projects/:project_id/todos/:todo_id/items/:id",
          "method": "get"
        },
        {
          "description": "Creating a new user todo",
          "link": "item/creating_a_new_user_todo.json",
          "groups": "all",
          "route": "/projects/:project_id/todos/:todo_id/items",
          "method": "post"
        },
        {
          "description": "Updating an specific user todo",
          "link": "item/updating_an_specific_user_todo.json",
          "groups": "all",
          "route": "/projects/:project_id/todos/:todo_id/items/:id",
          "method": "put"
        }
      ]
    },
    {
      "name": "Project",
      "explanation": null,
      "examples": [
        {
          "description": "Listing projects",
          "link": "project/listing_projects.json",
          "groups": "all",
          "route": "/projects",
          "method": "get"
        },
        {
          "description": "Getting a specific project",
          "link": "project/getting_a_specific_project.json",
          "groups": "all",
          "route": "/projects/:id",
          "method": "get"
        },
        {
          "description": "Creating a new project",
          "link": "project/creating_a_new_project.json",
          "groups": "all",
          "route": "/projects",
          "method": "post"
        },
        {
          "description": "Updating an specific project",
          "link": "project/updating_an_specific_project.json",
          "groups": "all",
          "route": "/projects/:id",
          "method": "put"
        }
      ]
    },
    {
      "name": "Todo",
      "explanation": null,
      "examples": [
        {
          "description": "Listing todos",
          "link": "todo/listing_todos.json",
          "groups": "all",
          "route": "/projects/:project_id/todos",
          "method": "get"
        },
        {
          "description": "Getting a specific todo from the login user",
          "link": "todo/getting_a_specific_todo_from_the_login_user.json",
          "groups": "all",
          "route": "/projects/:project_id/todos/:id",
          "method": "get"
        },
        {
          "description": "Creating a new user todo",
          "link": "todo/creating_a_new_user_todo.json",
          "groups": "all",
          "route": "/projects/:project_id/todos",
          "method": "post"
        },
        {
          "description": "Updating an specific user todo",
          "link": "todo/updating_an_specific_user_todo.json",
          "groups": "all",
          "route": "/projects/:project_id/todos/:id",
          "method": "put"
        }
      ]
    }
  ]
}